skmap/__init__.py
skmap/gapfiller.py
skmap/io.py
skmap/mapper.py
skmap/misc.py
skmap/plotter.py
skmap/qc.py
skmap/data/__init__.py
skmap/data/_defaults.py
skmap/data/_fallback.py
skmap/data/catalogue.py
skmap/data/toy.py
skmap/data/eo/__init__.py
skmap/data/eo/utils.py
skmap/data/eo/s2mosaic/__init__.py
skmap/data/eo/s2mosaic/job_executor.py
skmap/data/eo/s2mosaic/mosaic_helper.py
skmap/data/eo/s2mosaic/mosaic_maker.py
skmap/data/eo/s2mosaic/s2tiler.py
skmap/data/eo/s2mosaic/satmos_client.py
skmap/data/eo/s2mosaic/speedups.py
skmap/data/eo/s2mosaic/_dist_data/__init__.py
skmap/data/eo/s2mosaic/_dist_data/s2a_rel_orbit_gh.geojson
skmap/data/lucas/__init__.py
skmap/data/lucas/analyze.py
skmap/data/lucas/exceptions.py
skmap/data/lucas/io.py
skmap/data/lucas/logger.py
skmap/data/lucas/request.py
skmap/io/__init__.py
skmap/io/base.py
skmap/io/process.py
skmap/parallel/__init__.py
skmap/parallel/blocks.py
skmap/parallel/utils.py
skmap/transform/__init__.py
skmap/transform/fill.py
skmap/transform/smooth.py
tests/__init__.py
tests/test_misc.py
scikit_map-0.7.0.dist-info/LICENSE
scikit_map-0.7.0.dist-info/METADATA
scikit_map-0.7.0.dist-info/WHEEL
scikit_map-0.7.0.dist-info/top_level.txt
scikit_map-0.7.0.dist-info/RECORD
